i3alter/i3alter.py
i3alter/i3con.py
i3alter/keycapture.py
i3alter-0.1.0.dist-info/entry_points.txt
i3alter-0.1.0.dist-info/LICENSE
i3alter-0.1.0.dist-info/WHEEL
i3alter-0.1.0.dist-info/METADATA
i3alter-0.1.0.dist-info/RECORD
