Metadata-Version: 2.1
Name: i3alter
Version: 0.1.0
Summary: Add alt-tab behaviour to i3
License: MIT
Author: Kamyab Taghizadeh
Author-email: kamyab.zad@gmail.com
Requires-Python: >=3.7
Classifier: License :: OSI Approved :: MIT License
Classifier: Programming Language :: Python :: 3
Classifier: Programming Language :: Python :: 3.7
Classifier: Programming Language :: Python :: 3.8
Classifier: Programming Language :: Python :: 3.9
Requires-Dist: i3ipc (>=2.2.1,<3.0.0)
Requires-Dist: pynput (>=1.7.3,<2.0.0)
